Metadata-Version: 2.4
Name: tsearch
Version: 1.0.14
Summary: Package for uploads folder
Home-page: https://github.com/yourusername/uploads-parent
Author: xakuyaya
Author-email: your.email@example.com
Classifier: Programming Language :: Python :: 3
Classifier: License :: OSI Approved :: MIT License
Classifier: Operating System :: OS Independent
Requires-Python: >=3.7
Dynamic: author
Dynamic: author-email
Dynamic: classifier
Dynamic: description-content-type
Dynamic: home-page
Dynamic: requires-python
Dynamic: summary
